{
  "collectionName": "components_page_metadata",
  "info": {
    "displayName": "Metadata",
    "icon": "information",
    "description": ""
  },
  "options": {},
  "attributes": {
    "title": {
      "type": "string"
    },
    "description": {
      "type": "text"
    },
    "ogTitle": {
      "type": "string"
    },
    "ogDescription": {
      "type": "text"
    },
    "ogImage": {
      "allowedTypes": [
        "images"
      ],
      "type": "media",
      "multiple": false
    }
  }
}
